mcp_a2a_gateway/__init__.py
mcp_a2a_gateway/__main__.py
mcp_a2a_gateway/agent_manager.py
mcp_a2a_gateway/config.py
mcp_a2a_gateway/data_manager.py
mcp_a2a_gateway/main.py
mcp_a2a_gateway/server.py
mcp_a2a_gateway/task_manager.py
mcp_a2a_gateway-0.1.7.dist-info/METADATA
mcp_a2a_gateway-0.1.7.dist-info/WHEEL
mcp_a2a_gateway-0.1.7.dist-info/entry_points.txt
mcp_a2a_gateway-0.1.7.dist-info/licenses/LICENSE
mcp_a2a_gateway-0.1.7.dist-info/RECORD
