Metadata-Version: 2.4
Name: mcp-a2a-gateway
Version: 0.1.7
Summary: A bridge server that connects Model Context Protocol (MCP) with Agent-to-Agent (A2A) protocol
Project-URL: Homepage, https://github.com/yw0nam/mcp-a2a-gateway
Project-URL: Bug Tracker, https://github.com/yw0nam/mcp-a2a-gateway/issues
Project-URL: Repository, https://github.com/yw0nam/mcp-a2a-gateway
Project-URL: Documentation, https://github.com/yw0nam/mcp-a2a-gateway/blob/main/README.md
Author-email: yw0nam <spow2544@gmail.com>
Maintainer-email: yw0nam <spow2544@gmail.com>
License: Apache-2.0
License-File: LICENSE
Keywords: A2A,AI,Agent-to-Agent,LLM,MCP,Model Context Protocol,uvx
Classifier: Development Status :: 4 - Beta
Classifier: Environment :: Console
Classifier: Intended Audience :: Developers
Classifier: License :: OSI Approved :: Apache Software License
Classifier: Programming Language :: Python :: 3
Classifier: Programming Language :: Python :: 3.11
Classifier: Topic :: Scientific/Engineering :: Artificial Intelligence
Classifier: Topic :: Software Development :: Libraries :: Python Modules
Requires-Python: >=3.11
Requires-Dist: a2a-sdk>=0.2.8
Requires-Dist: fastmcp>=2.8.1
Requires-Dist: httpx>=0.28.1
Requires-Dist: uvicorn>=0.34.0
Provides-Extra: dev
Requires-Dist: black>=23.0.0; extra == 'dev'
Requires-Dist: flake8>=6.0.0; extra == 'dev'
Requires-Dist: isort>=5.12.0; extra == 'dev'
Requires-Dist: pytest-asyncio>=1.0.0; extra == 'dev'
Requires-Dist: pytest>=8.4.1; extra == 'dev'
Provides-Extra: test
Requires-Dist: pytest-asyncio>=1.0.0; extra == 'test'
Requires-Dist: pytest>=8.4.1; extra == 'test'
